structio.py
structio-1.4.2.dist-info/METADATA
structio-1.4.2.dist-info/WHEEL
structio-1.4.2.dist-info/top_level.txt
structio-1.4.2.dist-info/RECORD
