Metadata-Version: 2.2
Name: structio
Version: 1.4.2
Summary: A Library for unparsing, parsing, and editing binary files
Project-URL: Homepage, https://github.com/lingeringwillx/StructIO
Requires-Python: >=3.8
